heatmap_cli/__init__.py
heatmap_cli/__main__.py
heatmap_cli/cli.py
heatmap_cli/heatmap.py
heatmap_cli-0.22.13.dist-info/licenses/LICENSE.md
heatmap_cli-0.22.13.dist-info/METADATA
heatmap_cli-0.22.13.dist-info/WHEEL
heatmap_cli-0.22.13.dist-info/entry_points.txt
heatmap_cli-0.22.13.dist-info/top_level.txt
heatmap_cli-0.22.13.dist-info/RECORD
